nyt_prb_scraper-0.0.10.dist-info/DESCRIPTION.rst
nyt_prb_scraper-0.0.10.dist-info/METADATA
nyt_prb_scraper-0.0.10.dist-info/RECORD
nyt_prb_scraper-0.0.10.dist-info/WHEEL
nyt_prb_scraper-0.0.10.dist-info/entry_points.txt
nyt_prb_scraper-0.0.10.dist-info/metadata.json
nyt_prb_scraper-0.0.10.dist-info/top_level.txt
prb/__init__.py
