Metadata-Version: 2.0
Name: nyt-prb-scraper
Version: 0.0.10
Summary: A client for scraping and parsing the Periodic Review Secretariat's web page for Guananamo detainees.
Home-page: https://github.com/newsdev/nyt-prb-scraper
Author: Jeremy Bowers
Author-email: jeremy.bowers@nytimes.com
License: Apache License 2.0
Keywords: national security guantanamo bay criminal justice department of defense
Platform: UNKNOWN
Requires-Dist: beautifulsoup4
Requires-Dist: lxml
Requires-Dist: python-dateutil
Requires-Dist: requests
Requires-Dist: ujson
